scrapy_spider_auto_repair-0.1.4.dist-info/METADATA
scrapy_spider_auto_repair-0.1.4.dist-info/RECORD
scrapy_spider_auto_repair-0.1.4.dist-info/WHEEL
scrapy_spider_auto_repair-0.1.4.dist-info/top_level.txt
spider_auto_repair/Data Extractor.py
spider_auto_repair/__init__.py
spider_auto_repair/auto_repair_api.py
spider_auto_repair/auto_repair_code.py
spider_auto_repair/data_extractor_scrapy.py
